WebChatGPT/__init__.py
WebChatGPT/__main__.py
WebChatGPT/console.py
WebChatGPT/errors.py
WebChatGPT/main.py
WebChatGPT/utils.py
webchatgpt-0.3.0.dist-info/LICENSE
webchatgpt-0.3.0.dist-info/METADATA
webchatgpt-0.3.0.dist-info/WHEEL
webchatgpt-0.3.0.dist-info/entry_points.txt
webchatgpt-0.3.0.dist-info/top_level.txt
webchatgpt-0.3.0.dist-info/RECORD
