Metadata-Version: 2.1
Name: webchatgpt
Version: 0.3.0
Summary: Reverse Engineering of ChatGPT Web-Version
Home-page: https://github.com/Simatwa/WebChatGPT
Author: Smartwa
Author-email: simatwacaleb@proton.me
Maintainer: Smartwa
License: GNU v3
Project-URL: Bug Report, https://github.com/Simatwa/WebChatGPT/issues/new
Project-URL: Homepage, https://github.com/Simatwa/WebChatGPT
Project-URL: Source Code, https://github.com/Simatwa/WebChatGPT
Project-URL: Issue Tracker, https://github.com/Simatwa/WebChatGPT/issues
Project-URL: Download, https://github.com/Simatwa/WebChatGPT/releases
Project-URL: Documentation, https://github.com/Simatwa/WebChatGPT/blob/main/docs/README.md
Keywords: chatgpt,webchatgpt,gpt,chatgpt-cli,chatgpt-sdk,chatgpt-api
Classifier: License :: OSI Approved :: GNU General Public License v3 (GPLv3)
Classifier: Intended Audience :: Developers
Classifier: Intended Audience :: Developers
Classifier: Natural Language :: English
Classifier: License :: Free For Home Use
Classifier: Intended Audience :: Customer Service
Classifier: Programming Language :: Python
Classifier: Topic :: Software Development :: Libraries :: Python Modules
Classifier: Topic :: Scientific/Engineering :: Artificial Intelligence
Classifier: Programming Language :: Python :: 3 :: Only
Classifier: Programming Language :: Python :: 3.10
Classifier: Programming Language :: Python :: 3.11
Classifier: Programming Language :: Python :: 3.12
Requires-Python: >=3.10
License-File: LICENSE
Requires-Dist: requests ==2.31.0
Requires-Dist: python-dotenv ==1.0.0
Requires-Dist: click ==8.1.3
Requires-Dist: rich ==13.3.4
Requires-Dist: clipman ==3.1.0
Requires-Dist: pyperclip ==1.8.2
